python_wiiu_ristretto/__init__.py
python_wiiu_ristretto/hardware.py
python_wiiu_ristretto/wiiu.py
python_wiiu_ristretto-1.1.3.dist-info/licenses/LICENSE
python_wiiu_ristretto-1.1.3.dist-info/METADATA
python_wiiu_ristretto-1.1.3.dist-info/WHEEL
python_wiiu_ristretto-1.1.3.dist-info/top_level.txt
python_wiiu_ristretto-1.1.3.dist-info/RECORD
