Metadata-Version: 2.4
Name: python_wiiu_ristretto
Version: 1.1.3
Summary: Wrapper for communicating with Wii U consoles using the Ristretto API
Author-email: Joshua Peisach <itzswirlz2020@outlook.com>
License-Expression: GPL-3.0-only
Project-URL: Homepage, https://github.com/ItzSwirlz/python-wiiu-ristretto
Project-URL: Issues, https://github.com/ItzSwirlz/python-wiiu-ristretto/issues
Classifier: Programming Language :: Python :: 3
Classifier: Operating System :: OS Independent
Requires-Python: >=3.10
License-File: LICENSE
Requires-Dist: asyncio
Requires-Dist: aiohttp
Dynamic: license-file
